kite-1.5.8.dist-info/LICENSE.md
kite-1.5.8.dist-info/RECORD
kite-1.5.8.dist-info/WHEEL
kite-1.5.8.dist-info/entry_points.txt
kite-1.5.8.dist-info/top_level.txt
kite-1.5.8.dist-info/METADATA
kite/plot2d.py
kite/scene_processing.py
kite/scene_stack.py
kite/scene_mask.py
kite/qt_utils.py
kite/aps.py
kite/scene_io.py
kite/covariance.py
kite/__init__.py
kite/covariance_ext.cpython-311-darwin.so
kite/scene.py
kite/gacos.py
kite/quadtree.py
kite/deramp.py
kite/clients.py
kite/plugin.py
kite/sandbox_scene.py
kite/util/__init__.py
kite/util/bbd2kite.py
kite/util/stamps2kite.py
kite/talpa/config.py
kite/talpa/tool_dialogs.py
kite/talpa/sources_dock.py
kite/talpa/util.py
kite/talpa/sandbox_model.py
kite/talpa/__init__.py
kite/talpa/talpa.py
kite/talpa/__main__.py
kite/talpa/multiplot.py
kite/talpa/res/talpa_splash.png
kite/talpa/res/pyrocko_rectangular_source.ui
kite/talpa/res/pCDM_source.ui
kite/talpa/res/pyrocko_ringfault.ui
kite/talpa/res/pyrocko_moment_tensor.ui
kite/talpa/res/talpa-splash-full.png
kite/talpa/res/dialog_config.ui
kite/talpa/res/about.ui
kite/talpa/res/ellipsoid_source.ui
kite/talpa/res/okada_source.ui
kite/talpa/res/dialog_extent.ui
kite/talpa/res/dialog_los.ui
kite/talpa/res/pyrocko_double_couple.ui
kite/talpa/res/talpa.ui
kite/talpa/res/spin_widget.ui
kite/talpa/res/pyrocko_vlvd_source.ui
kite/talpa/res/window_reference.ui
kite/talpa/sources/compound_models.py
kite/talpa/sources/pyrocko.py
kite/talpa/sources/__init__.py
kite/talpa/sources/okada.py
kite/talpa/sources/base.py
kite/ext/covariance.c
kite/spool/scene_model.py
kite/spool/tab_covariance.py
kite/spool/spool.py
kite/spool/__init__.py
kite/spool/tab_scene.py
kite/spool/tab_aps.py
kite/spool/__main__.py
kite/spool/base.py
kite/spool/tab_quadtree.py
kite/spool/res/noise_dialog.ui
kite/spool/res/logging.ui
kite/spool/res/weight_matrix.ui
kite/spool/res/gacos_correction.ui
kite/spool/res/radar_splash.png
kite/spool/res/spool.ui
kite/spool/res/about.ui
kite/spool/res/transect.ui
kite/spool/res/spool_splash.png
kite/spool/res/boxkite-sketch.jpg
kite/sources/compound_sources.py
kite/sources/__init__.py
