Metadata-Version: 2.1
Name: kite
Version: 1.5.8
Summary: InSAR unwrapped surface displacement processing for earthquake modelling.
Author-email: Marius Paul Isken <mi@gfz-potsdam.de>, Henriette Sudhaus <hsudhaus@ifg.uni-kiel.de>
Maintainer-email: Marius Paul Isken <mi@gfz-potsdam.de>
License: GPLv3
Project-URL: Home, https://pyrocko.org
Project-URL: GitHub, https://github.com/pyrocko/kite
Project-URL: Issues, https://github.com/pyrocko/kite/issues
Keywords: InSAR,satellite,radar,earthquake,optimization
Classifier: Intended Audience :: Science/Research
Classifier: Topic :: Scientific/Engineering
Classifier: Topic :: Scientific/Engineering :: Atmospheric Science
Classifier: Topic :: Scientific/Engineering :: Image Recognition
Classifier: Topic :: Scientific/Engineering :: Physics
Classifier: Topic :: Scientific/Engineering :: Visualization
Classifier: Programming Language :: Python :: 3.7
Classifier: Programming Language :: C
Classifier: Operating System :: POSIX
Classifier: Operating System :: MacOS
Requires-Python: >=3.7
License-File: LICENSE.md
Requires-Dist: numpy>=1.17.3
Requires-Dist: scipy>=1.6.0
Requires-Dist: PyQt5>=5.15.0
Requires-Dist: pyqtgraph>=0.11.0
Requires-Dist: pyrocko>=2022.06.10
Requires-Dist: utm>=0.7.0
Requires-Dist: geojson>=2.5.0
Provides-Extra: gdal
Requires-Dist: gdal>=3.2.0; extra == "gdal"
Provides-Extra: development
Requires-Dist: flake8; extra == "development"
Requires-Dist: black; extra == "development"
Requires-Dist: pre-commit; extra == "development"
Provides-Extra: tests
Requires-Dist: pytest; extra == "tests"
